csvtotable/__init__.py
csvtotable/cli.py
csvtotable/convert.py
csvtotable/templates/template.html
csvtotable/templates/template.j2
csvtotable/templates/js/buttons.html5.min.js
csvtotable/templates/js/buttons.print.min.js
csvtotable/templates/js/dataTables.buttons.min.js
csvtotable/templates/js/dataTables.fixedHeader.min.js
csvtotable/templates/js/dataTables.scroller.min.js
csvtotable/templates/js/jquery.dataTables.min.js
csvtotable/templates/js/jquery.min.js
csvtotable-2.1.1.dist-info/DESCRIPTION.rst
csvtotable-2.1.1.dist-info/METADATA
csvtotable-2.1.1.dist-info/RECORD
csvtotable-2.1.1.dist-info/WHEEL
csvtotable-2.1.1.dist-info/entry_points.txt
csvtotable-2.1.1.dist-info/metadata.json
csvtotable-2.1.1.dist-info/top_level.txt
